pycommand/__init__.py
pycommand/__main__.py
pycommand/pycommand.py
pycommand/templates.py
pycommand/util.py
pycommand-0.4.0.data/data/share/pycommand/LICENSE
pycommand-0.4.0.data/data/share/pycommand/README.rst
pycommand-0.4.0.data/data/share/pycommand/examples/basic-example
pycommand-0.4.0.data/data/share/pycommand/examples/full-example
pycommand-0.4.0.dist-info/DESCRIPTION.rst
pycommand-0.4.0.dist-info/METADATA
pycommand-0.4.0.dist-info/RECORD
pycommand-0.4.0.dist-info/WHEEL
pycommand-0.4.0.dist-info/metadata.json
pycommand-0.4.0.dist-info/top_level.txt
