Metadata-Version: 2.0
Name: pycommand
Version: 0.4.0
Summary: Library / toolkit for creating command line programs with minimal effort.
Home-page: https://babab.github.io/pycommand/
Author: Benjamin Althues
Author-email: benjamin@babab.nl
License: ISC
Download-URL: http://pypi.python.org/pypi/pycommand/
Platform: any
Classifier: Development Status :: 5 - Production/Stable
Classifier: Environment :: Console
Classifier: Intended Audience :: Developers
Classifier: License :: OSI Approved :: ISC License (ISCL)
Classifier: Natural Language :: English
Classifier: Operating System :: OS Independent
Classifier: Programming Language :: Python :: 2.7
Classifier: Programming Language :: Python :: 3
Classifier: Topic :: Software Development :: Libraries :: Python Modules
Classifier: Topic :: System :: Shells
Classifier: Topic :: System :: Software Distribution
Classifier: Topic :: Terminals
Classifier: Topic :: Utilities
